fluidgrids/__init__.py
fluidgrids/ai.py
fluidgrids/auth.py
fluidgrids/base.py
fluidgrids/client.py
fluidgrids/config.py
fluidgrids/credentials.py
fluidgrids/dashboard.py
fluidgrids/exceptions.py
fluidgrids/models.py
fluidgrids/nodes.py
fluidgrids/runs.py
fluidgrids/search.py
fluidgrids/usage.py
fluidgrids/workflows.py
fluidgrids-0.1.0.dist-info/licenses/LICENSE
fluidgrids-0.1.0.dist-info/METADATA
fluidgrids-0.1.0.dist-info/WHEEL
fluidgrids-0.1.0.dist-info/top_level.txt
fluidgrids-0.1.0.dist-info/RECORD
