Metadata-Version: 2.4
Name: fluidgrids
Version: 0.1.0
Summary: Python SDK for the FluidGrids Workflow Engine
Home-page: https://fluidgrids.ai/
Author: Vignesh T.V
Author-email: vignesh@algoshred.com
Project-URL: Bug Tracker, https://github.com/algoshred/fluidgrids/issues
Project-URL: Documentation, https://docs.fluidgrids.ai/sdk
Project-URL: Source Code, https://github.com/algoshred/fluidgrids
Classifier: Programming Language :: Python :: 3
Classifier: Programming Language :: Python :: 3.8
Classifier: Programming Language :: Python :: 3.9
Classifier: Programming Language :: Python :: 3.10
Classifier: License :: OSI Approved :: MIT License
Classifier: Operating System :: OS Independent
Classifier: Development Status :: 4 - Beta
Classifier: Intended Audience :: Developers
Classifier: Topic :: Software Development :: Libraries :: Python Modules
Requires-Python: >=3.8
License-File: LICENSE
Requires-Dist: requests>=2.25.0
Requires-Dist: pydantic>=2.0.0
Requires-Dist: python-dateutil>=2.8.2
Dynamic: author
Dynamic: author-email
Dynamic: classifier
Dynamic: description
Dynamic: description-content-type
Dynamic: home-page
Dynamic: license-file
Dynamic: project-url
Dynamic: requires-dist
Dynamic: requires-python
Dynamic: summary
